{
  "forge_marker": 1,
  "defaults": { "textures": {
    "cross": "#flower",
    "layer0": "#flower"
  }},
  "variants": {
    "block": {
      "true": { "model": "cross" },
      "false": { 
        "transform": "forge:default-item",
        "model": "forge:item-layer"
      }
    },
    "type": {
      "rose":    { "textures": { "flower": "inspirations:blocks/flower_rose" }},
      "syringa": { "textures": { "flower": "inspirations:blocks/flower_syringa" }},
      "paeonia": { "textures": { "flower": "inspirations:blocks/flower_paeonia" }},
      "cyan":    { "textures": { "flower": "inspirations:blocks/flower_cyan" }}
    }
  }
}
