{
  "parent": "minecraft:recipes/root",
  "rewards": {
    "recipes": [
      "inspirations:utility/torch_lever"
    ]
  },
  "criteria": {
    "has_torch": {
      "trigger": "minecraft:inventory_changed",
      "conditions": {
        "items": [
          {
            "item": "minecraft:torch"
          }
        ]
      }
    },
    "has_lever": {
      "trigger": "minecraft:inventory_changed",
      "conditions": {
        "items": [
          {
            "item": "minecraft:lever"
          }
        ]
      }
    },
    "has_the_recipe": {
      "trigger": "minecraft:recipe_unlocked",
      "conditions": {
        "recipe": "inspirations:utility/torch_lever"
      }
    }
  },
  "requirements": [
    [
      "has_torch",
      "has_lever",
      "has_the_recipe"
    ]
  ]
}